tornado_jinja2/__init__.py
tornado_jinja2/integration.py
tornado_jinja2-0.2.4.dist-info/DESCRIPTION.rst
tornado_jinja2-0.2.4.dist-info/METADATA
tornado_jinja2-0.2.4.dist-info/RECORD
tornado_jinja2-0.2.4.dist-info/WHEEL
tornado_jinja2-0.2.4.dist-info/entry_points.txt
tornado_jinja2-0.2.4.dist-info/metadata.json
tornado_jinja2-0.2.4.dist-info/top_level.txt
