Metadata-Version: 1.1
Name: tornado-jinja2
Version: 0.2.4
Summary: jinja2 Engine for tornado web framework
Home-page: https://github.com/mr-ping/tornado_jinja2
Author: Mr-Ping
Author-email: yuanta11@gmail.com
License: MIT
Keywords: tornado jinja2 template engine python
Platform: UNKNOWN
Classifier: Development Status :: 4 - Beta
Classifier: Intended Audience :: Developers
Classifier: Topic :: Software Development :: Libraries :: Python Modules
Classifier: License :: OSI Approved :: MIT License
Classifier: Programming Language :: Python :: 2
Classifier: Programming Language :: Python :: 2.6
Classifier: Programming Language :: Python :: 2.7
Classifier: Programming Language :: Python :: 3
Classifier: Programming Language :: Python :: 3.3
Classifier: Programming Language :: Python :: 3.4
Classifier: Programming Language :: Python :: 3.5
